[
  {
    "name": "Kasseler unter Gemüserahm",
    "link": "kasseler-unter-gemüserahm",
    "tags": [
      "herzhaft",
      "kochen",
      "tomaten",
      "hauptgericht",
      "garten",
      "gemüse",
      "basmatireis",
      "porree",
      "pilze",
      "champignon",
      "sahne",
      "auflauf",
      "käse",
      "gäste",
      "schwein",
      "outtakes"
    ]
  },
  {
    "name": "Haselnusskuchen mit Nougatkern",
    "link": "haselnusskuchen-mit-nougatkern",
    "tags": [
      "süß",
      "backen",
      "gebäck",
      "kuchen",
      "haselnüsse",
      "spekulatius",
      "picknick",
      "nougat",
      "vanille",
      "outtakes"
    ]
  },
  {
    "name": "Rote-Bete-Suppe mit Gemüse-Crunch",
    "link": "rote-bete-suppe-mit-gemüse-crunch",
    "tags": [
      "veggie",
      "herzhaft",
      "kochen",
      "suppe",
      "maus",
      "aceto-balsamico",
      "vorspeise",
      "hauptgericht",
      "krimidinner",
      "garten",
      "winter",
      "weihnachten",
      "gemüse",
      "zwiebeln",
      "knoblauch",
      "bowl",
      "one-pot",
      "gäste",
      "weißwein",
      "rote-bete",
      "kartoffeln"
    ]
  },
  {
    "name": "Kräuterschweinchen",
    "link": "kräuterschweinchen",
    "witzig": true,
    "tags": [
      "herzhaft",
      "backen",
      "plätzchen",
      "kekse",
      "gebäck",
      "kräuter",
      "geburtstag",
      "mitbringsel",
      "silvester",
      "frischkäse",
      "dinkelmehl"
    ]
  },
  {
    "name": "Tomaten-Marmelade",
    "link": "tomaten-marmelade",
    "tags": [
      "herzhaft",
      "marmelade",
      "chutney",
      "salsa",
      "tortilla",
      "picknick",
      "garten",
      "tomate"
    ]
  },
  {
    "name": "Pilz-Päckchen",
    "link": "pilz-päckchen",
    "tags": [
      "herzhaft",
      "herbst",
      "gäste",
      "geburtstag",
      "buffet",
      "picknick",
      "party",
      "blätterteig",
      "champignons",
      "bergkäse",
      "frischkäse",
      "kochschinken",
      "thymian",
      "backen"
    ]
  },
  {
    "name": "Hedwig-plumpst-in-den-Schokotopf-Kürbis-Muffins",
    "link": "hedwig-plumpst-in-den-schokotopf-kürbis-muffins",
    "witzig": true,
    "tags": [
      "süß ",
      "backen",
      "gebäck",
      "kuchen",
      "muffin ",
      "harry-potter ",
      "herbst ",
      "halloween",
      "dinkelmehl",
      "rosinen",
      "kürbis",
      "zimt",
      "mitbringsel",
      "buffet",
      "geburtstag",
      "garten",
      "picknick",
      "winter",
      "herbst",
      "schokolade",
      "zettelz"
    ]
  },
  {
    "name": "Feldsalat mit Rote Bete und Waldnüssen",
    "link": "feldsalat-mit-rote-bete-und-waldnüssen",
    "tags": [
      "herzhaft",
      "kochen",
      "salat",
      "herbst",
      "winter",
      "gäste",
      "vorspeise",
      "picknick",
      "garten",
      "feldsalat",
      "rote bete",
      "walnüsse",
      "aceto-balsamico"
    ]
  },
  {
    "name": "Chili con Carne mit Schokolade",
    "link": "chili-con-carne-mit-schokolade",
    "witzig": true,
    "tags": [
      "herzhaft",
      "kochen",
      "bowl",
      "one-pot",
      "update",
      "party",
      "schokolade",
      "kidney-bohnen",
      "rinderhack",
      "chili",
      "creme fraiche",
      "herbst",
      "winter",
      "gäste",
      "geburtstag",
      "mode"
    ]
  },
  {
    "name": "Bavette mit Maronen-Creme & karamellisierten Walnüssen",
    "link": "bavette-mit-maronen-creme-karamellisierten-walnüssen",
    "tags": [
      "herzhaft",
      "pasta",
      "nudeln",
      "kochen",
      "herbst",
      "winter",
      "bowl",
      "maronen",
      "zwiebeln",
      "schalotten",
      "frischkäse",
      "ricotta",
      "walnüsse",
      "koriander",
      "petersilie"
    ]
  },
  {
    "name": "Honigmöhren vom Blech",
    "link": "honigmöhren-vom-blech",
    "tags": [
      "herzhaft",
      "herbst",
      "winter",
      "blech",
      "backen",
      "kochen",
      "asiatisch",
      "beilage",
      "garten",
      "gemüse",
      "hauptgericht",
      "möhren",
      "honig",
      "kreuzkümmel"
    ]
  },
  {
    "name": "Orangen-Kürbissuppe mit Zimt-Croutons",
    "link": "orangen-kürbissuppe-mit-zimt-croutons",
    "tags": [
      "herzhaft",
      "suppe",
      "herbst",
      "winter",
      "krimidinner",
      "garten",
      "kürbis",
      "orange",
      "ingwer",
      "zimt",
      "vorspeise",
      "maus"
    ]
  },
  {
    "name": "Senfgratin mit Pastinake & Kartoffeln",
    "link": "senfgratin-mit-pastinake-und-kartoffeln",
    "tags": [
      "veggie",
      "herzhaft",
      "kochen",
      "weißweinessig",
      "hauptgericht",
      "garten",
      "herbst",
      "winter",
      "auflauf",
      "beilage",
      "gemüse",
      "weißwein",
      "thymian",
      "senf",
      "pastinake",
      "kartoffeln",
      "hobel"
    ]
  },
  {
    "name": "Kohl & Pinkel klassisch",
    "link": "kohl-und-pinkel-klassisch",
    "witzig": true,
    "tags": [
      "herzhaft",
      "kochen",
      "hauptgericht",
      "kohltour",
      "glück-auf",
      "garten",
      "winter",
      "gemüse",
      "grünkohl",
      "kartoffeln",
      "zwiebeln",
      "kasseler",
      "piment",
      "senf"
    ]
  },
  {
    "name": "Röst-Rosenkohlsuppe mit karamellisierten Walnüssen & Chilifäden",
    "link": "röst-rosenkohlsuppe-mit-karamellisierten-walnüssen-und-chilifäden",
    "tags": [
      "veggie",
      "herzhaft",
      "kochen",
      "suppe",
      "kräuter",
      "majoran",
      "hauptgericht",
      "maus",
      "garten",
      "winter",
      "herbst",
      "gemüse",
      "honig",
      "kartoffeln",
      "walnüsse",
      "bowl",
      "chili"
    ]
  },
  {
    "name": "Bunter Focaccia-Garten",
    "link": "bunter-focaccia-garten",
    "tags": [
      "gebäck",
      "dinkelmehl",
      "kräuter",
      "tomate",
      "geburtstag",
      "party",
      "mitbringsel",
      "garten",
      "winter",
      "frühling",
      "sommer",
      "herbst",
      "blech",
      "gemüse",
      "kürbis",
      "möhren",
      "zwiebeln",
      "petersilie",
      "schnittlauch",
      "buffet",
      "dill",
      "thymian"
    ]
  },
  {
    "name": "Blueberry-Crumble",
    "link": "blueberry-crumble",
    "tags": [
      "süß",
      "backen",
      "kuchen",
      "dinkelmehl",
      "geburtstag",
      "mitbringsel",
      "nachtisch",
      "krimidinner",
      "mandeln",
      "gäste",
      "england"
    ]
  },
  {
    "name": "Küchlein für die kleinen Löffelfreunde",
    "link": "küchlein-für-die-kleinen-löffelfreunde",
    "tags": [
      "winter",
      "vogelfutter",
      "torte",
      "muffins"
    ]
  },
  {
    "name": "Apfel liebt Mandel",
    "link": "apfel-liebt-mandel",
    "witzig": true,
    "tags": [
      "süß",
      "backen",
      "gebäck ",
      "kuchen",
      "apfel",
      "apfelkuchen",
      "mandel ",
      "vanille ",
      "zimt",
      "dinkelmehl",
      "garten",
      "herbst",
      "honig",
      "gäste"
    ]
  },
  {
    "name": "Pasta mit Tomaten-Ingwer-Sugo",
    "link": "pasta-mit-tomaten-ingwer-sugo",
    "tags": [
      "veggie",
      "herzhaft",
      "kochen",
      "kräuter",
      "basilikum",
      "hauptgericht",
      "garten",
      "sommer",
      "gemüse ",
      "update ",
      "bowl ",
      "pasta",
      "nudeln",
      "knoblauch ",
      "schnell",
      "tomate ",
      "zwiebel ",
      "ingwer ",
      "orange ",
      "hobel"
    ]
  },
  {
    "name": "Apfel-Ziegenkäse-Burger",
    "link": "apfel-ziegenkäse-burger",
    "tags": [
      "herzhaft",
      "süß",
      "kochen",
      "backen",
      "kräuter",
      "thymian",
      "balsamico-bianco",
      "vorspeise",
      "herbst",
      "winter",
      "orange",
      "honig",
      "haselnüsse",
      "update",
      "salat",
      "gäste",
      "senf",
      "apfel",
      "ziegenkäse"
    ]
  },
  {
    "name": "Nuss-Makronen mit Schoko-Topping",
    "link": "nuss-makronen-mit-schoko-topping",
    "witzig": true,
    "tags": [
      "süß",
      "backen",
      "gebäck",
      "kokos",
      "haselnüsse",
      "mandeln",
      "winter",
      "mitbringsel",
      "weihnachten",
      "schokolade",
      "kekse",
      "plätzchen",
      "makronen",
      "schnell"
    ]
  },
  {
    "name": "Lila-Laune-Suppe",
    "link": "lila-laune-suppe",
    "tags": [
      "veggie",
      "herzhaft",
      "kochen",
      "suppe",
      "maus",
      "kräuter",
      "thymian",
      "rotkohl",
      "rote-zwiebeln",
      "kartoffeln",
      "apfel",
      "vorspeise",
      "garten",
      "winter",
      "herbst",
      "one-pot",
      "bowl",
      "gäste",
      "schmand",
      "weißwein"
    ]
  },
  {
    "name": "Knuspriger Zander auf Fenchelrisotto mit Granatapfel-Gremolata",
    "link": "knuspriger-zander-auf-fenchelrisotto-mit-granatapfel-gremolata",
    "tags": [
      "herzhaft",
      "fisch",
      "risotto ",
      "bowl",
      "hobel",
      "zander",
      "fenchel",
      "granatapfel",
      "zwiebel",
      "pinienkerne",
      "kochen",
      "hauptgericht",
      "winter",
      "kräuter",
      "petersilie",
      "zitrone"
    ]
  },
  {
    "name": "Zupfkuchen mit ganz viel Herz",
    "link": "zupfkuchen-mit-ganz-viel-herz",
    "tags": [
      "süß",
      "backen",
      "kuchen",
      "dinkelmehl",
      "quark",
      "valentinstag",
      "kakao",
      "mitbringsel",
      "gäste",
      "klassiker"
    ]
  },
  {
    "name": "Süsskartoffelsüppchen mit Baconchips und löffelweise Cassis",
    "link": "süsskartoffelsüppchen-mit-baconchips-und-löffelweise-cassis",
    "tags": [
      "herzhaft",
      "kochen",
      "suppe",
      "kräuter",
      "schnittlauch",
      "party",
      "gäste",
      "maus",
      "vorspeise",
      "hauptgericht",
      "maus",
      "garten",
      "herbst",
      "winter",
      "gemüse",
      "möhren",
      "süßkartoffeln",
      "schalotten",
      "bowl",
      "creme-fraîche",
      "aceto-balsamico"
    ]
  },
  {
    "name": "Maulwurfkuchen mit vergrabenen Kirschen",
    "link": "maulwurfkuchen-mit-vergrabenen-kirschen",
    "witzig": true,
    "tags": [
      "veggie",
      "süß",
      "backen",
      "kuchen",
      "torte",
      "dinkelmehl",
      "geburtstag",
      "maus",
      "schokolade",
      "kirsche",
      "sahne",
      "marzipan"
    ]
  },
  {
    "name": "Ofen-Köttbullar mit Preiselbeer-Relish",
    "link": "ofen-köttbullar-mit-preiselbeer-relish",
    "tags": [
      "herzhaft",
      "kochen",
      "backen",
      "hauptgericht",
      "blech",
      "one-pot",
      "auflauf",
      "update",
      "schweden",
      "chutney",
      "rinderhack",
      "creme-fraîche",
      "aceto-balsamico",
      "champignon",
      "pilze",
      "gouda"
    ]
  },
  {
    "name": "Schokokuchen mit roter Grütze",
    "link": "schokokuchen-mit-roter-grütze",
    "witzig": true,
    "tags": [
      "süß",
      "backen",
      "kuchen",
      "dinkelmehl",
      "picknick",
      "schokolade",
      "früchte",
      "gäste",
      "update",
      "buffet",
      "vanille",
      "schnell",
      "einfach"
    ]
  },
  {
    "name": "Wachtelei in Champignon",
    "link": "wachtelei-in-champignon",
    "tags": [
      "veggie",
      "herzhaft",
      "vorspeise",
      "kochen",
      "kräuter",
      "champignon",
      "pilze",
      "garten",
      "frühling",
      "ostern",
      "beilage",
      "gemüse",
      "zwiebeln",
      "knoblauch",
      "walnüsse",
      "salat",
      "feldsalat",
      "senf"
    ]
  },
  {
    "name": "Hasenbrötchen",
    "link": "hasenbrötchen",
    "witzig": true,
    "tags": [
      "süß",
      "backen",
      "gebäck",
      "dinkelmehl",
      "mitbringsel",
      "brunch",
      "ostern",
      "picknick",
      "frühling",
      "gäste"
    ]
  },
  {
    "name": "Bärlauch-Butter",
    "link": "bärlauch-butter",
    "tags": [
      "veggie",
      "herzhaft",
      "kräuter",
      "bärlauch",
      "grillen",
      "frühling",
      "gäste",
      "schnell",
      "brot"
    ]
  },
  {
    "name": "Bärlauch-Cashew-Aufstrich",
    "link": "bärlauch-cashew-aufstrich",
    "tags": [
      "veggie",
      "herzhaft",
      "frischkäse",
      "kräuter",
      "bärlauch",
      "cashew",
      "picknick",
      "frühling",
      "gäste",
      "schnell",
      "hobel",
      "brot",
      "westfälisch"
    ]
  },
  {
    "name": "Bärlauch-Parmesan-Crêpes",
    "link": "bärlauch-parmesan-crepes",
    "tags": [
      "veggie",
      "herzhaft",
      "backen",
      "dinkelmehl",
      "kräuter ",
      "bärlauch",
      "vorspeise",
      "frühling",
      "update",
      "gäste",
      "frankreich",
      "weißwein",
      "parmesan",
      "hobel"
    ]
  },
  {
    "name": "Bärlauch-Cappuccino",
    "link": "bärlauch-cappuccino",
    "tags": [
      "veggie",
      "herzhaft",
      "kochen",
      "suppe",
      "kräuter",
      "bärlauch",
      "vorspeise",
      "maus",
      "garten",
      "frühling",
      "gemüse",
      "zwiebeln",
      "bowl",
      "one-pot",
      "gäste",
      "prosecco",
      "creme-fraîche",
      "erbsen"
    ]
  },
  {
    "name": "Osterlämmchen",
    "link": "osterlämmchen",
    "witzig": true,
    "tags": [
      "süß",
      "backen",
      "gebäck",
      "kuchen",
      "dinkelmehl",
      "ostern",
      "picknick",
      "brunch",
      "frühling",
      "vanille",
      "update"
    ]
  },
  {
    "name": "Holunderblüten-Sirup",
    "link": "holunderblüten-sirup",
    "tags": [
      "veggie",
      "süß",
      "getränk",
      "holunder",
      "sommer",
      "aperitif",
      "gäste",
      "prosecco",
      "sekt",
      "zitrone",
      "limette",
      "alkohol"
    ]
  },
  {
    "name": "Antipasti aus grünem Spargel",
    "link": "antipasti-aus-grünem-spargel",
    "tags": [
      "veggie",
      "herzhaft",
      "italien",
      "italienisch",
      "kräuter",
      "petersilie",
      "olive",
      "kapern ",
      "grüner-spargel",
      "tomaten",
      "balsamico-bianco",
      "vorspeise",
      "buffet",
      "gäste",
      "frühling",
      "sommer",
      "gemüse",
      "zwiebeln",
      "update",
      "parmaschinken",
      "schnell"
    ]
  },
  {
    "name": "Erdbeer-Limes",
    "link": "erdbeer-limes",
    "tags": [
      "alkohol",
      "veggie",
      "erdbeere",
      "wodka",
      "vanille",
      "getränk",
      "aperitif",
      "likör",
      "garten",
      "gäste",
      "mitbringsel",
      "sommer",
      "schnell"
    ]
  },
  {
    "name": "Warmer Spargelsalat weiss-grün",
    "link": "warmer-spargelsalat-weiss-grün",
    "tags": [
      "veggie",
      "herzhaft",
      "kochen",
      "tomaten",
      "vorspeise",
      "garten",
      "frühling",
      "gemüse",
      "spargel",
      "rucola",
      "zwiebeln",
      "gurke",
      "feta",
      "bowl",
      "update",
      "gäste",
      "zitrone"
    ]
  },
  {
    "name": "Marsala-Likör",
    "link": "marsala-likör",
    "tags": [
      "alkohol",
      "getränk",
      "rotwein",
      "kaffee",
      "mitbringsel",
      "italienisch",
      "Italien",
      "gäste",
      "kandis",
      "kaffee"
    ]
  },
  {
    "name": "Erdbeer-Törtchen",
    "link": "erdbeer-törtchen",
    "witzig": true,
    "tags": [
      "süß",
      "backen",
      "gebäck",
      "torte",
      "kuchen",
      "dinkelmehl",
      "garten",
      "sommer",
      "mandeln",
      "update",
      "gäste",
      "marmelade"
    ]
  },
  {
    "name": "Erdbeermarmelade mit rosa Pfeffer",
    "link": "erdbeermarmelade-mit-rosa-pfeffer",
    "tags": [
      "süß",
      "herzhaft",
      "veggie",
      "erdbeere",
      "balsamico-bianco",
      "rosa-pfeffer",
      "mitbringsel",
      "geschenk",
      "frühstück",
      "sommer",
      "update",
      "marmelade",
      "schweden"
    ]
  },
  {
    "name": "Zitronenkuchen im Kasten",
    "link": "zitronenkuchen-im-kasten",
    "witzig": true,
    "tags": [
      "süß",
      "backen",
      "kuchen",
      "dinkelmehl",
      "geburtstag",
      "mitbringsel",
      "picknick",
      "zitrone"
    ]
  },
  {
    "name": "Rhabarber-Flammkuchen",
    "link": "rhababer-flammkuchen",
    "tags": [
      "veggie",
      "herzhaft",
      "backen",
      "frischkäse",
      "ziegenkäse",
      "dinkelmehl",
      "kräuter",
      "thymian",
      "rosa-pfeffer",
      "ahornsirup",
      "gäste",
      "rhabarbara",
      "garten",
      "sommer",
      "blech",
      "zwiebeln",
      "weißwein",
      "cidre",
      "créme-fraîche"
    ]
  },
  {
    "name": "Erdbeer-Joghurt-Tarte",
    "link": "erdbeer-joghurt-tarte",
    "tags": [
      "süß",
      "veggie",
      "gebäck",
      "kuchen",
      "schokolade",
      "erdbeere",
      "joghurt",
      "garten",
      "sommer",
      "gäste",
      "tarte",
      "lavendelfeld",
      "honig",
      "holunderblüte",
      "camper"
    ]
  },
  {
    "name": "Mandel-Macchiato on Ice",
    "link": "mandel-macchiato-on-ice",
    "tags": [
      "süß",
      "getränk",
      "espresso",
      "kaffee",
      "garten",
      "sommer",
      "nachtisch",
      "keks",
      "gäste",
      "schnell",
      "alkohol"
    ]
  },
  {
    "name": "Aprikose-Lavendel-Marmelade",
    "link": "aprikose-lavendel-marmelade",
    "tags": [
      "süß",
      "frühstück",
      "lavendel",
      "lavendelfeld",
      "aprikose",
      "mitbringsel",
      "spoonies",
      "garten",
      "picknick",
      "sommer",
      "update",
      "marmelade",
      "konfitüre",
      "kräuter"
    ]
  },
  {
    "name": "Rhabarberkuchen mit Baiserhaube",
    "link": "rhabarberkuchen-mit-baiserhaube",
    "tags": [
      "süß",
      "veggie",
      "backen",
      "kuchen",
      "torte",
      "dinkelmehl",
      "garten",
      "sommer",
      "zitrone",
      "rhabarbara"
    ]
  },
  {
    "name": "Erdbeer-Chili-Chutney",
    "link": "erdbeer-chili-chutney",
    "tags": [
      "herzhaft",
      "veggie",
      "kochen",
      "erdbeeren",
      "zwiebeln",
      "zimt",
      "balsamico-bianco",
      "mitbringsel",
      "vorspeise",
      "spoonies",
      "garten",
      "chili",
      "picknick",
      "sommer",
      "rotwein",
      "käse",
      "gäste",
      "chutney",
      "ingwer"
    ]
  },
  {
    "name": "Erdbeersalat an Avocadomus",
    "link": "erdbeersalat-an-avocadomus",
    "tags": [
      "veggie",
      "süß",
      "mascarpone",
      "erdbeere",
      "avocado",
      "sahne",
      "zitrone",
      "balsamico-bianco",
      "nachtisch",
      "dessert",
      "spoonies",
      "garten",
      "sommer",
      "holunder",
      "gäste",
      "schnell"
    ]
  },
  {
    "name": "Schoko-Muffins mit cremigem Kern",
    "link": "schoko-muffins-mit-cremigem-kern",
    "witzig": true,
    "tags": [
      "süß",
      "kuchen",
      "muffin",
      "geburtstag",
      "party",
      "schokolade",
      "mode"
    ]
  },
  {
    "name": "Kartoffelsuppe mit Streifen vom Räucherlachs & Pumpernickel-Würfel",
    "link": "kartoffelsuppe-mit-streifen-vom-räucherlachs-und-pumpernickel-würfel",
    "tags": [
      "herzhaft",
      "veggie",
      "kochen",
      "suppe",
      "kräuter",
      "schnittlauch",
      "gäste",
      "maus",
      "garten",
      "kartoffeln",
      "zwiebel",
      "knoblauch",
      "bowl",
      "one-pot",
      "update",
      "westfälisch",
      "schnell"
    ]
  },
  {
    "name": "Sommer-Tiramisu mit Balsamico-Erdbeeren ",
    "link": "sommer-tiramisu-mit-balsamico-erdbeeren",
    "tags": [
      "süß",
      "veggie",
      "dessert",
      "sommer",
      "erdbeeren",
      "mascarpone",
      "aceto-balsamico",
      "spoonies",
      "gäste",
      "buffet",
      "brunch",
      "nachspeise",
      "kuchen",
      "garten",
      "italien",
      "update"
    ]
  },
  {
    "name": "Rhabarber-Tarte",
    "link": "rhababer-tarte",
    "tags": [
      "süß",
      "veggie",
      "backen",
      "gebäck",
      "kuchen",
      "tarte",
      "dinkelmehl",
      "schmand",
      "rhabarbara",
      "rhabarber",
      "himbeer",
      "vanille",
      "mandeln",
      "puderzucker",
      "zitrone",
      "rosmarin"
    ]
  },
  {
    "name": "Wild-Bratwurst auf Mango-Curry-Bett",
    "link": "wild-bratwurst-auf-mango-curry-bett",
    "tags": [
      "herzhaft",
      "kochen",
      "grillen",
      "balsamico-bianco",
      "gäste",
      "sommer",
      "update",
      "beilage",
      "gewürz",
      "curry",
      "zwiebel",
      "petersilie",
      "kräuter",
      "wild",
      "ingwer",
      "tomate"
    ]
  },
  {
    "name": "Curry-Dattel-Crème",
    "link": "curry-dattel-creme",
    "tags": [
      "veggie",
      "herzhaft",
      "frischkäse",
      "dattel",
      "curry",
      "cashew",
      "party",
      "grillen",
      "picknick",
      "buffet",
      "schnell",
      "spoonies"
    ]
  },
  {
    "name": "Gebratene Mie-Nudeln mit Curry-Pute",
    "link": "gebratene-mie-nudeln-mit-curry-pute",
    "tags": [
      "herzhaft",
      "kochen",
      "hauptgericht",
      "asiatisch",
      "bowl",
      "one-pot",
      "gemüse",
      "pasta",
      "nudeln",
      "zwiebeln",
      "pute",
      "paprika",
      "erbsen",
      "soja",
      "curry",
      "schnell"
    ]
  },
  {
    "name": "Salt & Wonder \"Coffee-Vanilla\"",
    "link": "salt-and-wonder-coffee-vanilla",
    "tags": [
      "gewürz",
      "salz",
      "mitbringsel",
      "winter",
      "update",
      "kaffee",
      "schnell",
      "vanille",
      "grillen"
    ]
  },
  {
    "name": "Schokolade DARK & ROSE",
    "link": "schokolade-dark-and-rose",
    "tags": [
      "süß",
      "backen",
      "schokolade",
      "haselnuss",
      "himbeere",
      "kirsche",
      "früchte",
      "naschen",
      "geburtstag",
      "mitbringsel",
      "nachtisch",
      "rose",
      "gäste",
      "schnell",
      "mode"
    ]
  },
  {
    "name": "Joghurteis mit Rosenduft & Mango-Swirl",
    "link": "joghurteis-mit-rosenduft-und-mango-swirl",
    "tags": [
      "veggie",
      "süß",
      "eis",
      "joghurt",
      "himbeere",
      "mango",
      "nachtisch",
      "gäste",
      "sommer",
      "rose",
      "update"
    ]
  },
  {
    "name": "Hähnchen in Pergament im Orange-Senf-Sud",
    "link": "hähnchen-in-pergament-im-orange-senf-sud",
    "tags": [
      "herzhaft",
      "kochen",
      "hähnchen",
      "senf",
      "olive",
      "zwiebel",
      "orange",
      "rucola",
      "hauptgericht",
      "schnell",
      "gäste",
      "blech",
      "exotisch",
      "geflügel"
    ]
  },
  {
    "name": "Kokos-Mohn-Popsicles mit Himbeerexplosion",
    "link": "kokos-mohn-popsicles-mit-himbeerexplosion",
    "tags": [
      "veggie",
      "süß",
      "eis",
      "gäste",
      "himbeere",
      "kokos",
      "mohn",
      "kardamom",
      "gewürz",
      "schnell",
      "nachtisch",
      "sommer",
      "honig"
    ]
  },
  {
    "name": "Zitronenkuchen grüne Wiese",
    "link": "zitronenkuchen-grüne-wiese",
    "witzig": true,
    "tags": [
      "süß",
      "kuchen",
      "update",
      "geburtstag",
      "spinat",
      "zitrone"
    ]
  },
  {
    "name": "Zwiebeltarte mit Pflaumen",
    "link": "zwiebeltarte-mit-pflaumen",
    "tags": [
      "update",
      "herzhaft",
      "tarte",
      "herbst",
      "frankreich",
      "lavendelfeld",
      "garten",
      "weißwein",
      "federweißer",
      "federroter",
      "traubensaft",
      "zwiebeln",
      "pflaume",
      "mürbteig"
    ]
  },
  {
    "name": "Hähnchen mit Dattel-Spinatfüllung & süssen Beten",
    "link": "hähnchen-mit-dattelspinatfüllung",
    "tags": [
      "herzhaft",
      "kochen",
      "kräuter",
      "rosmarin",
      "tomaten",
      "hauptgericht",
      "gäste",
      "krimidinner",
      "one pot",
      "herbst",
      "winter",
      "blech",
      "kreuzkümmel ",
      "spinat",
      "zwiebeln",
      "hähnchen",
      "rote bete"
    ]
  },
  {
    "name": "Rauchfisch-Carbonara an Sepia-Spaghetti",
    "link": "rauchfisch-carbonara-an-sepia-spaghetti",
    "tags": [
      "herzhaft",
      "kochen",
      "kräuter",
      "hauptgericht",
      "garten",
      "gemüse",
      "zucchini",
      "pasta",
      "nudeln",
      "zwiebeln",
      "italien",
      "fisch",
      "parmesan",
      "oregano",
      "forelle",
      "hobel",
      "schnell"
    ]
  },
  {
    "name": "Klassische Knusperwaffel nach Opa Heinz",
    "link": "klassische-knusperwaffel-nach-opa-heinz",
    "tags": [
      "zettelz",
      "veggie",
      "süß",
      "backen",
      "gebäck",
      "kuchen",
      "dinkelmehl",
      "dessert",
      "picknick",
      "erdbeere",
      "kirsche"
    ]
  },
  {
    "name": "Feigentöpfchen mit Rotwein & Walnüssen",
    "link": "feigentöpfchen-mit-rotwein-und-walnüssen",
    "tags": [
      "veggie",
      "süß",
      "kochen",
      "party",
      "mitbringsel",
      "spoonies",
      "picknick",
      "herbst",
      "rotwein",
      "walnuss",
      "gäste",
      "käse",
      "feige",
      "chutney",
      "wild"
    ]
  },
  {
    "name": "Pak Choi an Chili-Ingwer-Hähnchen",
    "link": "pak-choi-an-chili-ingwer-hähnchen",
    "tags": [
      "herzhaft",
      "kochen",
      "hauptgericht",
      "herbst",
      "winter",
      "asiatisch",
      "basmatireis",
      "knoblauch",
      "chili",
      "limette",
      "ingwer",
      "hähnchenbrust",
      "sojasauce"
    ]
  },
  {
    "name": "Christmas Caprese",
    "link": "christmas-caprese",
    "tags": [
      "herzhaft",
      "vorspeise",
      "weihnachten",
      "mozzarella",
      "tomaten",
      "balsamico-bianco"
    ]
  },
  {
    "name": "Vanille-Kipferl",
    "link": "vanille-kipferl",
    "tags": [
      "veggie",
      "süß",
      "backen",
      "naschen",
      "plätzchen",
      "gebäck",
      "kekse",
      "dinkelmehl",
      "vanille",
      "winter",
      "weihnachten",
      "blech",
      "haselnuss",
      "mandel",
      "mürbteig"
    ]
  },
  {
    "name": "Zimt-Mascarpone-Torte",
    "link": "zimt-mascarpone-torte",
    "witzig": true,
    "tags": [
      "süß",
      "kuchen",
      "torte",
      "winter",
      "weihnachten",
      "mascarpone",
      "zimt",
      "spekulatius",
      "quark"
    ]
  },
  {
    "name": "Snowball Cookies",
    "link": "snowball-cookies",
    "witzig": true,
    "tags": [
      "süß",
      "backen",
      "plätzchen",
      "kekse",
      "gebäck",
      "dinkelmehl",
      "kokos",
      "weihnachten",
      "winter",
      "mitbringsel"
    ]
  },
  {
    "name": "Granatapfel-Glühwein",
    "link": "granatapfel-glühwein",
    "tags": [
      "süß",
      "getränk",
      "winter",
      "weihnachten",
      "rotwein",
      "granatapfel",
      "orange",
      "zimt",
      "sternanis"
    ]
  },
  {
    "name": "Spritzgebäck",
    "link": "spritzgebäck",
    "witzig": true,
    "tags": [
      "süß",
      "backen",
      "gebäck",
      "plätzchen",
      "kekse",
      "weihnachten",
      "winter",
      "schokolade"
    ]
  },
  {
    "name": "Weihnachtlicher Apfel-Stern-Kuchen",
    "link": "weihnachtlicher-apfel-stern-kuchen",
    "tags": [
      "veggie",
      "süß",
      "backen",
      "gebäck",
      "kuchen ",
      "apfel",
      "dinkelmehl",
      "zimt",
      "winter",
      "weihnachten",
      "haselnüsse",
      "schnell",
      "garten"
    ]
  },
  {
    "name": "Winterlicher Grünkohl-Salat mit Paradiesapfel",
    "link": "winterlicher-grünkohl-salat-mit-paradiesapfel",
    "tags": [
      "veggie",
      "herzhaft",
      "kochen",
      "salat",
      "kohltour",
      "bowl",
      "update",
      "winter",
      "gemüse",
      "grünkohl",
      "gurke",
      "avocado",
      "feta",
      "honig",
      "senf"
    ]
  },
  {
    "name": "XMAS-Crunch",
    "link": "xmas-crunch",
    "tags": [
      "veggie",
      "süß",
      "backen",
      "naschen",
      "müsli",
      "zimt",
      "spekulatius",
      "frühstück",
      "walnüsse",
      "haselnüsse",
      "mandeln",
      "kürbiskerne",
      "sonnenblumenkerne",
      "agavendicksaft",
      "spoonies",
      "winter",
      "weihnachten",
      "blech",
      "bowl",
      "schnell"
    ]
  },
  {
    "name": "Weihnachtliches Tomaten-Chutney",
    "link": "weihnachtliches-tomaten-chutney",
    "tags": [
      "veggie",
      "herzhaft",
      "kochen",
      "einkochen",
      "tomaten",
      "kirschtomaten",
      "aceto-balsamico",
      "mitbringsel",
      "käse",
      "spoonieswinter",
      "weihnachten",
      "beilage",
      "gemüse",
      "knoblauch",
      "porree",
      "gäste",
      "buffet",
      "chutney",
      "schnell",
      "grillen"
    ]
  },
  {
    "name": "Lebkuchen-Männchen",
    "link": "lebkuchen-männchen",
    "tags": []
  },
  {
    "name": "XMAS-Gin-Tonic",
    "link": "xmas-gin-tonic",
    "tags": [
      "veggie",
      "süß",
      "naschen",
      "getränk",
      "drink",
      "aperitif",
      "silvester",
      "weihnachten",
      "winter",
      "granatapfel",
      "update",
      "rosmarin",
      "gäste",
      "gin",
      "schnell",
      "alkohol"
    ]
  },
  {
    "name": "Filet vom Reh auf Rahmspinat & Cranberries",
    "link": "filet-vom-reh-auf-rahmspinat-und-cranberries",
    "tags": [
      "herzhaft",
      "kochen",
      "kräuter",
      "thymian",
      "hauptgericht",
      "winter",
      "herbst",
      "weihnachten",
      "blech",
      "gemüse",
      "wild",
      "reh",
      "spinat",
      "cranberry",
      "zwiebeln",
      "limette",
      "honig",
      "rotwein",
      "niedrigenergie",
      "update",
      "gäste"
    ]
  },
  {
    "name": "Cheeseburger XMAS",
    "link": "cheeseburger-xmas",
    "tags": [
      "veggie",
      "herzhaft",
      "kochen",
      "kräuter",
      "rosmarin",
      "silvester",
      "weihnachten",
      "hauptgericht",
      "winter",
      "update",
      "senf",
      "brie",
      "rucola",
      "pilze",
      "champignon",
      "zwiebel",
      "honig",
      "haselnuss",
      "haselnüsse",
      "update"
    ]
  }
]